team_center_api/__init__.py
team_center_api/api.py
team_center_api/constants.py
team_center_api/log.py
team_center_api/six.py
team_center_api-0.2.12.dist-info/METADATA
team_center_api-0.2.12.dist-info/WHEEL
team_center_api-0.2.12.dist-info/top_level.txt
team_center_api-0.2.12.dist-info/RECORD
