Metadata-Version: 2.1
Name: team-center-api
Version: 0.2.12
Summary: team center api
Home-page: https://github.com/dantezhu/team_center
Author: dantezhu
Author-email: dantezhu <zny2008@gmail.com>
License: BSD
Project-URL: Homepage, https://github.com/dantezhu/team_center
Platform: any
Requires-Dist: requests
